stdpairs/__init__.py
stdpairs/_stdpairs.py
stdpairs/_string_interface.py
stdpairs/_zsolve_interface.py
stdpairs/affinemonoid.py
stdpairs/macaulay2_interface.py
stdpairs/monomialideal.py
stdpairs/properpair.py
stdpairs/txt_to_object.py
stdpairs-1.0.4.dist-info/LICENSE
stdpairs-1.0.4.dist-info/METADATA
stdpairs-1.0.4.dist-info/WHEEL
stdpairs-1.0.4.dist-info/top_level.txt
stdpairs-1.0.4.dist-info/RECORD
