Metadata-Version: 2.1
Name: stdpairs
Version: 1.0.4
Summary: A library of SageMath doing symbolic computation over a monomial ideal of an affine (non-normal) semigroup ring
Home-page: https://github.com/byeongsuyu/StdPairs
Author: Byeongsu Yu
Author-email: byeongsu.yu@gmail.com
License: UNKNOWN
Project-URL: Bug Tracker, https://github.com/byeongsuyu/StdPairs/issues
Platform: UNKNOWN
Classifier: Programming Language :: Python :: 3
Classifier: License :: OSI Approved :: GNU General Public License v3 (GPLv3)
Classifier: Operating System :: OS Independent
Requires-Python: >=3.9
